homonim/__init__.py
homonim/cli.py
homonim/compare.py
homonim/enums.py
homonim/errors.py
homonim/fuse.py
homonim/kernel_model.py
homonim/matched_pair.py
homonim/raster_array.py
homonim/raster_pair.py
homonim/stats.py
homonim/utils.py
homonim/version.py
homonim-0.4.3.dist-info/licenses/LICENSE
homonim-0.4.3.dist-info/METADATA
homonim-0.4.3.dist-info/WHEEL
homonim-0.4.3.dist-info/entry_points.txt
homonim-0.4.3.dist-info/top_level.txt
homonim-0.4.3.dist-info/RECORD
