Metadata-Version: 2.4
Name: homonim
Version: 0.4.3
Summary: Correct aerial and satellite imagery to surface reflectance.
Author: Leftfield Geospatial
License: AGPL-3.0-or-later
Project-URL: Homepage, https://github.com/leftfield-geospatial/homonim
Project-URL: Source, https://github.com/leftfield-geospatial/homonim
Project-URL: Documentation, https://homonim.readthedocs.io
Project-URL: Changelog, https://github.com/leftfield-geospatial/homonim/releases
Project-URL: Issues, https://github.com/leftfield-geospatial/homonim/issues
Keywords: drone,aerial,satellite,image,surface reflectance,correction,harmonization,anisotropy,brdf,atmospheric correction
Classifier: Programming Language :: Python :: 3
Classifier: License :: OSI Approved :: GNU Affero General Public License v3 or later (AGPLv3+)
Classifier: Operating System :: OS Independent
Requires-Python: >=3.9
License-File: LICENSE
Requires-Dist: rasterio>=1.1
Requires-Dist: opencv-python-headless>=4.5
Requires-Dist: numpy>=1.19
Requires-Dist: click>=8
Requires-Dist: tqdm>=4.6
Requires-Dist: pyyaml>=5.4
Requires-Dist: cloup>=0.15
Requires-Dist: tabulate>=0.8
Provides-Extra: test
Requires-Dist: pytest; extra == "test"
Dynamic: license-file
